interpreter/__init__.py
interpreter/app.py
interpreter/ast_nodes.py
interpreter/core.py
interpreter/lexer.py
interpreter/main.py
interpreter/mlscript.cp313-win_amd64.pyd
interpreter/mlscript.exp
interpreter/mlscript.lib
interpreter/parser.py
mlscript_kernel/__init__.py
mlscript_kernel/__main__.py
mlscript_kernel/install.py
mlscript_kernel/kernel.py
mlscript_kernel/kernelspec/kernel.json
mlscript_lang-1.0.0.dist-info/METADATA
mlscript_lang-1.0.0.dist-info/WHEEL
mlscript_lang-1.0.0.dist-info/entry_points.txt
mlscript_lang-1.0.0.dist-info/licenses/LICENSE
mlscript_lang-1.0.0.dist-info/RECORD
