Metadata-Version: 2.2
Name: mlscript-lang
Version: 1.0.0
Summary: A specialized scripting language for AI and Machine Learning.
Author-Email: Amit Singh <amitsinghdps6@gmail.com>
License: MIT License
Project-URL: Homepage, https://github.com/AmitSingh410/mlscript
Project-URL: Bug Tracker, https://github.com/AmitSingh410/mlscript/issues
Requires-Python: >=3.8
Requires-Dist: numpy
Requires-Dist: ipykernel
Requires-Dist: jupyter-client
Requires-Dist: ipython
